[
  {
    "id": 1,
    "logo": "assets/partners/BM.png"
  },
  {
    "id": 2,
    "logo": "assets/partners/BUDEKO.png"
  },
  {
    "id": 3,
    "logo": "assets/partners/Motor_Sich.png"
  },
  {
    "id": 4,
    "logo": "assets/partners/tbe.zp.ua.png"
  },
  {
    "id": 5,
    "logo": "assets/partners/ULMA.png"
  },
  {
    "id": 6,
    "logo": "assets/partners/ZLMZ.png"
  },
  {
    "id": 7,
    "logo": "assets/partners/metal-group.png"
  },
  {
    "id": 8,
    "logo": "assets/partners/met-invest.png"
  },
  {
    "id": 9,
    "logo": "assets/partners/ugostal.png"
  },
  {
    "id": 10,
    "logo": "assets/partners/pershii-dim.png"
  }
]
